sotrans_models/__init__.py
sotrans_models/models/__init__.py
sotrans_models/models/_base.py
sotrans_models/models/_mongo.py
sotrans_models/models/ads.py
sotrans_models/models/organizations.py
sotrans_models/models/responses.py
sotrans_models/models/roles.py
sotrans_models/models/sections.py
sotrans_models/models/users.py
sotrans_models/models/misc/__init__.py
sotrans_models/models/misc/client.py
sotrans_models/models/misc/document.py
sotrans_models/models/misc/verification.py
sotrans_models/models/orders/__init__.py
sotrans_models/models/orders/bid.py
sotrans_models/models/orders/order.py
sotrans_models/models/parsers/__init__.py
sotrans_models/models/parsers/fmlogistic.py
sotrans_models/models/parsers/scraped_api.py
sotrans_models/models/processes/__init__.py
sotrans_models/models/processes/bid_tracking.py
sotrans_models/models/processes/company_verification.py
sotrans_models/models/processes/notifications.py
sotrans_models/models/processes/processes.py
sotrans_models/models/resources/__init__.py
sotrans_models/models/resources/drivers.py
sotrans_models/models/resources/trailers.py
sotrans_models/models/resources/trucks.py
sotrans_models/utils/__init__.py
sotrans_models/utils/constrained_pydantic_types.py
sotrans_models/utils/make_partial_model.py
sotrans_models/utils/type_checks.py
sotrans_models-0.7.30.dist-info/METADATA
sotrans_models-0.7.30.dist-info/WHEEL
sotrans_models-0.7.30.dist-info/top_level.txt
sotrans_models-0.7.30.dist-info/RECORD
