Metadata-Version: 2.1
Name: sotrans-models
Version: 0.7.30
Requires-Python: >=3.10
Requires-Dist: annotated-types (==0.6.0)
Requires-Dist: pymongo (==4.5.0)
Requires-Dist: phonenumbers (==8.13.23)
Requires-Dist: email-validator (==2.1.0)
Requires-Dist: fastapi (==0.100.1)
Requires-Dist: idna (==3.4)
Requires-Dist: pydantic (==2.3.0)
Requires-Dist: certifi (==2023.7.22)
Requires-Dist: pydantic-extra-types (==2.0.0)
Requires-Dist: charset-normalizer (==3.2.0)
Requires-Dist: dnspython (==2.4.2)
Requires-Dist: ecdsa (==0.18.0)
Requires-Dist: rsa (==4.9)
Requires-Dist: six (==1.16.0)
Requires-Dist: sniffio (==1.3.0)
Requires-Dist: sotrans-fastapi-keycloak (~=1.2.1)
Requires-Dist: starlette (==0.27.0)
Requires-Dist: urllib3 (==2.0.4)
Requires-Dist: mongo-path (==1.1.0)
